gSheetsDataExtractor/__init__.py
gSheetsDataExtractor-0.0.1.dist-info/LICENCE.txt
gSheetsDataExtractor-0.0.1.dist-info/METADATA
gSheetsDataExtractor-0.0.1.dist-info/WHEEL
gSheetsDataExtractor-0.0.1.dist-info/top_level.txt
gSheetsDataExtractor-0.0.1.dist-info/RECORD
