Metadata-Version: 2.1
Name: gSheetsDataExtractor
Version: 0.0.1
Summary: Google sheets Data Extractor
Home-page: https://github.com/dhanush5120/
Author: Sai Dhanush
Author-email: dhanushsai5553@gmail.com
License: MIT
Keywords: dataExtractor
Platform: UNKNOWN
Classifier: Operating System :: OS Independent
Classifier: License :: OSI Approved :: MIT License
Classifier: Programming Language :: Python :: 3
Requires-Dist: pandas
Requires-Dist: matplotlib
